pynightmare/__init__.py
pynightmare/hello_world.py
pynightmare-0.0.1.dist-info/METADATA
pynightmare-0.0.1.dist-info/WHEEL
pynightmare-0.0.1.dist-info/top_level.txt
pynightmare-0.0.1.dist-info/RECORD
