Metadata-Version: 2.1
Name: pynightmare
Version: 0.0.1
Summary: Handling coding nightmware in Pythonic ways
Author: Mohsin Ashraf
Author-email: <mohsin.ashraf12@gmail.com>
Keywords: python,utils,aws,data
Classifier: Development Status :: 1 - Planning
Classifier: Intended Audience :: Developers
Classifier: Programming Language :: Python :: 3
Classifier: Operating System :: Unix
Classifier: Operating System :: MacOS :: MacOS X
Classifier: Operating System :: Microsoft :: Windows
Requires-Dist: pandas
Requires-Dist: boto3
